colors/__init__.py
colors/base.py
colors/primary.py
colors/rainbow.py
colors/w3c.py
colors.py-0.2.2.dist-info/DESCRIPTION.rst
colors.py-0.2.2.dist-info/METADATA
colors.py-0.2.2.dist-info/metadata.json
colors.py-0.2.2.dist-info/pbr.json
colors.py-0.2.2.dist-info/RECORD
colors.py-0.2.2.dist-info/top_level.txt
colors.py-0.2.2.dist-info/WHEEL
